ntp_shm/__init__.py
ntp_shm/__main__.py
ntp_shm/data.py
ntp_shm/main.py
ntp_shm/memory.py
ntp_shm/nmea.py
ntp_shm/util.py
ntp_shm-2.0.2.dist-info/LICENSE
ntp_shm-2.0.2.dist-info/METADATA
ntp_shm-2.0.2.dist-info/WHEEL
ntp_shm-2.0.2.dist-info/entry_points.txt
ntp_shm-2.0.2.dist-info/top_level.txt
ntp_shm-2.0.2.dist-info/RECORD
