Metadata-Version: 2.1
Name: ntp-shm
Version: 2.0.2
Summary: Pure Python NTP shared memory library.
Author-email: "Stefan R. Filipek" <srfilipek@gmail.com>
Project-URL: Homepage, https://gitlab.com/srfilipek/ntp-shm
Project-URL: Bug Tracker, https://gitlab.com/srfilipek/ntp-shm/-/issues
Keywords: gps,time,chrony,ntp,serial,shm,ntpshm
Classifier: Intended Audience :: Developers
Classifier: License :: OSI Approved :: MIT License
Classifier: Natural Language :: English
Classifier: Operating System :: OS Independent
Classifier: Programming Language :: Python :: 3
Classifier: Topic :: Software Development :: Libraries :: Python Modules
Classifier: Topic :: System :: Networking :: Time Synchronization
Requires-Python: >=3.7
License-File: LICENSE
Provides-Extra: dev
Requires-Dist: tox ; extra == 'dev'
Requires-Dist: pytest ; extra == 'dev'
Requires-Dist: black ; extra == 'dev'
Requires-Dist: isort ; extra == 'dev'
Requires-Dist: mypy ; extra == 'dev'
Requires-Dist: bumpversion ; extra == 'dev'
